mymcplusplus/__init__.py
mymcplusplus/__main__.py
mymcplusplus/mymc.py
mymcplusplus/ps2icon.py
mymcplusplus/ps2iconsys.py
mymcplusplus/ps2mc.py
mymcplusplus/ps2mc_dir.py
mymcplusplus/ps2mc_ecc.py
mymcplusplus/round.py
mymcplusplus/sjistab.py
mymcplusplus/utils.py
mymcplusplus/verbuild.py
mymcplusplus/gui/__init__.py
mymcplusplus/gui/dirlist_control.py
mymcplusplus/gui/gui.py
mymcplusplus/gui/icon_renderer.py
mymcplusplus/gui/icon_window.py
mymcplusplus/gui/linalg.py
mymcplusplus/gui/resources.py
mymcplusplus/gui/utils.py
mymcplusplus/save/__init__.py
mymcplusplus/save/format_codebreaker.py
mymcplusplus/save/format_ems.py
mymcplusplus/save/format_max_drive.py
mymcplusplus/save/format_psv.py
mymcplusplus/save/format_sharkport.py
mymcplusplus/save/lzari.py
mymcplusplus/save/ps2save.py
mymcplusplus/save/utils.py
mymcplusplus-3.1.0.dist-info/LICENSE
mymcplusplus-3.1.0.dist-info/METADATA
mymcplusplus-3.1.0.dist-info/WHEEL
mymcplusplus-3.1.0.dist-info/entry_points.txt
mymcplusplus-3.1.0.dist-info/top_level.txt
mymcplusplus-3.1.0.dist-info/RECORD
