Metadata-Version: 2.1
Name: mymcplusplus
Version: 3.1.0
Summary: A PlayStation 2 memory card manager
Home-page: https://github.com/Adubbz/mymcplusplus
Author: Adubbz
License: GPLv3
Keywords: playstation ps2 mymc memory card save
Requires-Python: >=3.4
License-File: LICENSE
Provides-Extra: gui
Requires-Dist: wxPython ; extra == 'gui'
Requires-Dist: pyopengl ; extra == 'gui'
